{"expireTime":9007200835517067000,"key":"transformer-remark-markdown-html-ast-35a47b4d1dd027d8c72948d24c079317-gatsby-remark-relative-imagesgatsby-remark-imagesgatsby-remark-lazy-loadgatsby-remark-prismjs-","val":{"type":"root","children":[{"type":"element","tagName":"p","properties":{},"children":[{"type":"text","value":"Digital minimalism helps us to question which digital tools add the most value to our lives. I think it’s extremely important to eliminate useless digital pursuits, and use the internet for a purpose that makes sense (creating or consuming something very useful). When we remove unnecessary things, we get time for what really matters.","position":{"start":{"line":2,"column":1,"offset":1},"end":{"line":2,"column":336,"offset":336}}}],"position":{"start":{"line":2,"column":1,"offset":1},"end":{"line":2,"column":336,"offset":336}}},{"type":"text","value":"\n"},{"type":"element","tagName":"p","properties":{},"children":[{"type":"text","value":"In short, adopting digital minimalism gives us more time to focus on what we think is essential for us.","position":{"start":{"line":4,"column":1,"offset":338},"end":{"line":4,"column":104,"offset":441}}}],"position":{"start":{"line":4,"column":1,"offset":338},"end":{"line":4,"column":104,"offset":441}}}],"position":{"start":{"line":1,"column":1,"offset":0},"end":{"line":6,"column":1,"offset":443}}}}